numpu/__init__.py
numpu/numpu.py
numpu-0.1.4.dist-info/METADATA
numpu-0.1.4.dist-info/WHEEL
numpu-0.1.4.dist-info/top_level.txt
numpu-0.1.4.dist-info/RECORD
