Metadata-Version: 2.1
Name: numpu
Version: 0.1.4
Summary: Quick chat shortcuts for g4f and HuggingFace models
Home-page: UNKNOWN
Author: aaaroo
Author-email: you@example.com
License: UNKNOWN
Platform: UNKNOWN
Requires-Python: >=3.7
